{
    "@context": {
        "@version": 1.1,
        "@protected": true,
        "id": "@id",
        "type": "@type",
        "schema": "https://schema.org/",
        "EducationCredential": {
            "@id": "schema:EducationCredential",
            "@context": {
                "id": "@id",
                "@version": 1.1,
                "@protected": true
            }
        },
        "Person": {
            "@id": "schema:Person",
            "@context": {
                "@version": 1.1,
                "@protected": true,
                "studentId": "schema:name",
                "percentage": "schema:name",
                "fullName": "schema:name",
                "UIN": "schema:name",
                "mobile": "schema:name",
                "email": "schema:name",
                "dob": "schema:name",
                "gender": "schema:name",
                "degree": "schema:name",
                "university":"schema:name"
            }
        }
    }
}
